{"name": "gf180mcu_fd_sc_mcu7t5v0__antenna", "bounding_box": [[-0.43, -0.43], [1.55, 4.3500000000000005]], "layers": {"112/1": {"name": "", "polygons": [[[0.0, 0.0], [0.0, 3.92], [1.12, 3.92], [1.12, 0.0]]], "labels": []}, "21/0": {"name": "Nwell", "polygons": [[[-0.43, 1.76], [-0.43, 4.3500000000000005], [1.55, 4.3500000000000005], [1.55, 1.76]]], "labels": []}, "204/0": {"name": "", "polygons": [[[-0.43, -0.43], [-0.43, 1.76], [1.55, 1.76], [1.55, -0.43]]], "labels": []}, "55/0": {"name": "", "polygons": [[[-0.28, -0.28], [-0.28, 4.2], [1.4000000000000001, 4.2], [1.4000000000000001, -0.28]]], "labels": []}, "32/0": {"name": "Nplus", "polygons": [[[-0.2, -0.2], [-0.2, 1.76], [1.32, 1.76], [1.32, -0.2]]], "labels": []}, "31/0": {"name": "Pplus", "polygons": [[[-0.2, 1.76], [-0.2, 4.12], [1.32, 4.12], [1.32, 1.76]]], "labels": []}, "22/0": {"name": "", "polygons": [[[0.18, 0.59], [0.18, 1.16], [0.54, 1.16], [0.54, 0.59]], [[0.18, 2.36], [0.18, 2.93], [0.54, 2.93], [0.54, 2.36]]], "labels": []}, "33/0": {"name": "Contact", "polygons": [[[0.25, 0.87], [0.25, 1.09], [0.47000000000000003, 1.09], [0.47000000000000003, 0.87]], [[0.25, 2.43], [0.25, 2.65], [0.47000000000000003, 2.65], [0.47000000000000003, 2.43]]], "labels": []}, "34/0": {"name": "Metal1", "polygons": [[[0.14, 0.81], [0.14, 2.71], [0.47500000000000003, 2.71], [0.47500000000000003, 0.81]], [[0.0, -0.3], [0.0, 0.3], [1.12, 0.3], [1.12, -0.3]], [[0.0, 3.62], [0.0, 4.22], [1.12, 4.22], [1.12, 3.62]]], "labels": []}, "0/0": {"name": "PR_bndry", "polygons": [[[0.0, 0.0], [0.0, 3.92], [1.12, 3.92], [1.12, 0.0]]], "labels": []}, "115/5": {"name": "", "polygons": [[[0.0, 0.0], [0.0, 3.92], [1.12, 3.92], [1.12, 0.0]]], "labels": []}, "34/10": {"name": "Metal1_Label", "polygons": [], "labels": [{"text": "VSS", "position": [0.28, 0.0], "anchor": 5, "rotation": null, "magnification": 0.2, "x_reflection": false}, {"text": "I", "position": [0.28, 1.96], "anchor": 5, "rotation": null, "magnification": 0.2, "x_reflection": false}, {"text": "VDD", "position": [0.28, 3.92], "anchor": 5, "rotation": null, "magnification": 0.2, "x_reflection": false}]}, "63/63": {"name": "", "polygons": [], "labels": [{"text": "& Vendor GLOBALFOUNDRIES", "position": [0.0, 2.0], "anchor": 4, "rotation": null, "magnification": 0.3, "x_reflection": false}, {"text": "& Product GF018hv5v_mcu_sc7", "position": [0.0, 1.5], "anchor": 4, "rotation": null, "magnification": 0.3, "x_reflection": false}, {"text": "& Version 2015q2v1", "position": [0.0, 1.0], "anchor": 4, "rotation": null, "magnification": 0.3, "x_reflection": false}, {"text": "& Metric 1.00", "position": [0.0, 0.5], "anchor": 4, "rotation": null, "magnification": 0.3, "x_reflection": false}]}}}