{"name": "gf180mcu_fd_sc_mcu7t5v0__nand4_1", "bounding_box": [[-0.43, -0.43], [5.47, 4.3500000000000005]], "layers": {"112/1": {"name": "", "polygons": [[[0.0, 0.0], [0.0, 3.92], [5.04, 3.92], [5.04, 0.0]]], "labels": []}, "21/0": {"name": "Nwell", "polygons": [[[-0.43, 1.76], [-0.43, 4.3500000000000005], [5.47, 4.3500000000000005], [5.47, 1.76]]], "labels": []}, "204/0": {"name": "", "polygons": [[[-0.43, -0.43], [-0.43, 1.76], [5.47, 1.76], [5.47, -0.43]]], "labels": []}, "55/0": {"name": "", "polygons": [[[-0.28, -0.28], [-0.28, 4.2], [5.32, 4.2], [5.32, -0.28]]], "labels": []}, "32/0": {"name": "Nplus", "polygons": [[[-0.2, -0.2], [-0.2, 1.76], [5.24, 1.76], [5.24, -0.2]]], "labels": []}, "31/0": {"name": "Pplus", "polygons": [[[-0.2, 1.76], [-0.2, 4.12], [5.24, 4.12], [5.24, 1.76]]], "labels": []}, "22/0": {"name": "", "polygons": [[[0.335, 0.34], [0.335, 1.16], [4.775, 1.16], [4.775, 0.34]], [[0.335, 2.73], [0.335, 3.575], [4.775, 3.575], [4.775, 2.73]]], "labels": []}, "30/0": {"name": "Poly2", "polygons": [[[0.775, 0.12], [0.775, 3.8000000000000003], [1.2750000000000001, 3.8000000000000003], [1.2750000000000001, 1.44], [1.375, 1.44], [1.375, 0.12]], [[1.745, 0.12], [1.745, 1.44], [1.795, 1.44], [1.795, 3.8000000000000003], [2.295, 3.8000000000000003], [2.295, 1.44], [2.345, 1.44], [2.345, 0.12]], [[2.765, 0.12], [2.765, 1.44], [2.815, 1.44], [2.815, 3.8000000000000003], [3.315, 3.8000000000000003], [3.315, 1.44], [3.365, 1.44], [3.365, 0.12]], [[3.735, 0.12], [3.735, 1.44], [3.835, 1.44], [3.835, 3.8000000000000003], [4.335, 3.8000000000000003], [4.335, 0.12]]], "labels": []}, "33/0": {"name": "Contact", "polygons": [[[0.405, 0.66], [0.405, 0.88], [0.625, 0.88], [0.625, 0.66]], [[0.405, 3.24], [0.405, 3.46], [0.625, 3.46], [0.625, 3.24]], [[0.93, 1.935], [0.93, 2.1550000000000002], [1.1500000000000001, 2.1550000000000002], [1.1500000000000001, 1.935]], [[1.425, 2.97], [1.425, 3.19], [1.645, 3.19], [1.645, 2.97]], [[1.875, 1.33], [1.875, 1.55], [2.095, 1.55], [2.095, 1.33]], [[2.445, 3.24], [2.445, 3.46], [2.665, 3.46], [2.665, 3.24]], [[2.96, 1.33], [2.96, 1.55], [3.18, 1.55], [3.18, 1.33]], [[3.465, 2.97], [3.465, 3.19], [3.685, 3.19], [3.685, 2.97]], [[4.045, 1.645], [4.045, 1.865], [4.265, 1.865], [4.265, 1.645]], [[4.485, 0.735], [4.485, 0.9550000000000001], [4.705, 0.9550000000000001], [4.705, 0.735]], [[4.485, 3.24], [4.485, 3.46], [4.705, 3.46], [4.705, 3.24]]], "labels": []}, "34/0": {"name": "Metal1", "polygons": [[[0.66, 1.21], [0.66, 2.19], [1.4000000000000001, 2.19], [1.4000000000000001, 1.8900000000000001], [1.02, 1.8900000000000001], [1.02, 1.21]], [[3.775, 0.53], [3.775, 0.98], [4.6000000000000005, 0.98], [4.6000000000000005, 2.715], [1.26, 2.715], [1.26, 3.39], [1.6500000000000001, 3.39], [1.6500000000000001, 2.945], [3.46, 2.945], [3.46, 3.39], [3.77, 3.39], [3.77, 2.95], [4.91, 2.95], [4.91, 0.53]], [[0.0, -0.3], [0.0, 0.3], [0.4, 0.3], [0.4, 0.98], [0.63, 0.98], [0.63, 0.3], [5.04, 0.3], [5.04, -0.3]], [[0.4, 3.18], [0.4, 3.62], [0.0, 3.62], [0.0, 4.22], [5.04, 4.22], [5.04, 3.62], [4.71, 3.62], [4.71, 3.18], [4.48, 3.18], [4.48, 3.62], [2.67, 3.62], [2.67, 3.18], [2.44, 3.18], [2.44, 3.62], [0.63, 3.62], [0.63, 3.18]], [[1.8, 0.61], [1.8, 2.19], [2.14, 2.19], [2.14, 0.61]], [[2.9, 0.61], [2.9, 2.19], [3.24, 2.19], [3.24, 0.61]], [[4.0200000000000005, 1.21], [4.0200000000000005, 2.19], [4.37, 2.19], [4.37, 1.21]]], "labels": []}, "0/0": {"name": "PR_bndry", "polygons": [[[0.0, 0.0], [0.0, 3.92], [5.04, 3.92], [5.04, 0.0]]], "labels": []}, "34/10": {"name": "Metal1_Label", "polygons": [], "labels": [{"text": "A3", "position": [1.96, 1.4000000000000001], "anchor": 5, "rotation": null, "magnification": 0.2, "x_reflection": false}, {"text": "A4", "position": [0.84, 1.96], "anchor": 5, "rotation": null, "magnification": 0.2, "x_reflection": false}, {"text": "VDD", "position": [2.52, 3.92], "anchor": 5, "rotation": null, "magnification": 0.2, "x_reflection": false}, {"text": "VSS", "position": [2.52, 0.0], "anchor": 5, "rotation": null, "magnification": 0.2, "x_reflection": false}, {"text": "ZN", "position": [3.64, 3.08], "anchor": 5, "rotation": null, "magnification": 0.2, "x_reflection": false}, {"text": "A1", "position": [4.2, 1.96], "anchor": 5, "rotation": null, "magnification": 0.2, "x_reflection": false}, {"text": "A2", "position": [3.08, 1.4000000000000001], "anchor": 5, "rotation": null, "magnification": 0.2, "x_reflection": false}]}, "63/63": {"name": "", "polygons": [], "labels": [{"text": "& Vendor GLOBALFOUNDRIES", "position": [0.0, 2.0], "anchor": 4, "rotation": null, "magnification": 0.3, "x_reflection": false}, {"text": "& Product GF018hv5v_mcu_sc7", "position": [0.0, 1.5], "anchor": 4, "rotation": null, "magnification": 0.3, "x_reflection": false}, {"text": "& Version 2015q2v1", "position": [0.0, 1.0], "anchor": 4, "rotation": null, "magnification": 0.3, "x_reflection": false}, {"text": "& Metric 1.00", "position": [0.0, 0.5], "anchor": 4, "rotation": null, "magnification": 0.3, "x_reflection": false}]}}}